Workbook

Sheet Extracted Data
A1: Company Name | B1: Ticker | C1: Fiscal Year | D1: Fiscal Year End | E1: Total Revenue | F1: Net Income | G1: Total Assets | H1: Total Liabilities | I1: Cash Flow from Operating Activities | J1: Revenue Growth (%) | K1: Net Income Growth (%) | L1: Operating Cash Flow Growth (%) | M1: Profit Margin (%) | N1: Liabilities / Assets (%) | O1: Source URL
A2: Microsoft | B2: MSFT | C2: 2023 | D2: 2023-06-30 | E2: 211915 | F2: 72361 | G2: 411976 | H2: 205753 | I2: 87582 | M2: =F2/E2 -> 0.34146238 | N2: =H2/G2 -> 0.49942958 | O2: https://www.microsoft.com/investor/reports/ar25/index.html
A3: Microsoft | B3: MSFT | C3: 2024 | D3: 2024-06-30 | E3: 245122 | F3: 88136 | G3: 512163 | H3: 243686 | I3: 118548 | J3: =IF(E2=0,"",(E3-E2)/E2) -> 0.15669962 | K3: =IF(F2=0,"",(F3-F2)/F2) -> 0.21800417 | L3: =IF(I2=0,"",(I3-I2)/I2) -> 0.3535658 | M3: =F3/E3 -> 0.35955973 | N3: =H3/G3 -> 0.47579774 | O3: https://www.microsoft.com/investor/reports/ar25/index.html
A4: Microsoft | B4: MSFT | C4: 2025 | D4: 2025-06-30 | E4: 281724 | F4: 101832 | G4: 619003 | H4: 275524 | I4: 136162 | J4: =IF(E3=0,"",(E4-E3)/E3) -> 0.14932156 | K4: =IF(F3=0,"",(F4-F3)/F3) -> 0.15539621 | L4: =IF(I3=0,"",(I4-I3)/I3) -> 0.14858117 | M4: =F4/E4 -> 0.36146015 | N4: =H4/G4 -> 0.44510931 | O4: https://www.microsoft.com/investor/reports/ar25/index.html
A5: Tesla | B5: TSLA | C5: 2023 | D5: 2023-12-31 | E5: 96773 | F5: 14974 | G5: 106618 | H5: 43009 | I5: 13256 | M5: =F5/E5 -> 0.15473324 | N5: =H5/G5 -> 0.40339342 | O5: https://stocklight.com/stocks/us/nasdaq-tsla/tesla/annual-reports/nasdaq-tsla-2026-10K-26574326.pdf
A6: Tesla | B6: TSLA | C6: 2024 | D6: 2024-12-31 | E6: 97690 | F6: 7153 | G6: 122070 | H6: 48390 | I6: 14923 | J6: =IF(E5=0,"",(E6-E5)/E5) -> 0.0094757835 | K6: =IF(F5=0,"",(F6-F5)/F5) -> -0.52230533 | L6: =IF(I5=0,"",(I6-I5)/I5) -> 0.12575438 | M6: =F6/E6 -> 0.073221415 | N6: =H6/G6 -> 0.39641189 | O6: https://stocklight.com/stocks/us/nasdaq-tsla/tesla/annual-reports/nasdaq-tsla-2026-10K-26574326.pdf
A7: Tesla | B7: TSLA | C7: 2025 | D7: 2025-12-31 | E7: 94827 | F7: 3855 | G7: 137806 | H7: 54941 | I7: 14747 | J7: =IF(E6=0,"",(E7-E6)/E6) -> -0.029306992 | K7: =IF(F6=0,"",(F7-F6)/F6) -> -0.46106529 | L7: =IF(I6=0,"",(I7-I6)/I6) -> -0.011793875 | M7: =F7/E7 -> 0.040652979 | N7: =H7/G7 -> 0.39868366 | O7: https://stocklight.com/stocks/us/nasdaq-tsla/tesla/annual-reports/nasdaq-tsla-2026-10K-26574326.pdf
A8: Apple | B8: AAPL | C8: 2023 | D8: 2023-09-30 | E8: 383285 | F8: 96995 | G8: 352583 | H8: 290437 | I8: 110543 | M8: =F8/E8 -> 0.25306234 | N8: =H8/G8 -> 0.82374079 | O8: https://www.sec.gov/Archives/edgar/data/320193/000032019325000079/aapl-20250927.htm
A9: Apple | B9: AAPL | C9: 2024 | D9: 2024-09-28 | E9: 391035 | F9: 93736 | G9: 364980 | H9: 308030 | I9: 118254 | J9: =IF(E8=0,"",(E9-E8)/E8) -> 0.020219941 | K9: =IF(F8=0,"",(F9-F8)/F8) -> -0.03359967 | L9: =IF(I8=0,"",(I9-I8)/I8) -> 0.069755661 | M9: =F9/E9 -> 0.23971256 | N9: =H9/G9 -> 0.84396405 | O9: https://www.sec.gov/Archives/edgar/data/320193/000032019325000079/aapl-20250927.htm
A10: Apple | B10: AAPL | C10: 2025 | D10: 2025-09-27 | E10: 416161 | F10: 112010 | G10: 359241 | H10: 285508 | I10: 111482 | J10: =IF(E9=0,"",(E10-E9)/E9) -> 0.064255118 | K10: =IF(F9=0,"",(F10-F9)/F9) -> 0.19495178 | L10: =IF(I9=0,"",(I10-I9)/I9) -> -0.057266562 | M10: =F10/E10 -> 0.26915064 | N10: =H10/G10 -> 0.79475338 | O10: https://www.sec.gov/Archives/edgar/data/320193/000032019325000079/aapl-20250927.htm

Sheet Summary
A1: Financial Data Analysis Summary
A2: Company | B2: Ticker | C2: 2025 Revenue | D2: 2025 Net Income | E2: Revenue CAGR 2023-2025 | F2: Net Income CAGR 2023-2025 | G2: Avg Revenue Growth | H2: Avg Net Income Growth | I2: 2025 Profit Margin | J2: Interpretation
A3: Microsoft | B3: MSFT | C3: 281724 | D3: 101832 | E3: =('Extracted Data'!E4-'Extracted Data'!E2)/'Extracted Data'!E2 -> 0.32941981 | F3: =('Extracted Data'!F4-'Extracted Data'!F2)/'Extracted Data'!F2 -> 0.4072774 | G3: =AVERAGE('Extracted Data'!J3:J4) -> 0.15301059 | H3: =AVERAGE('Extracted Data'!K3:K4) -> 0.18670019 | I3: ='Extracted Data'!M4 -> 0.36146015 | J3: Strong growth across revenue, net income, and operating cash flow; profitability remained high.
A4: Tesla | B4: TSLA | C4: 94827 | D4: 3855 | E4: =('Extracted Data'!E7-'Extracted Data'!E5)/'Extracted Data'!E5 -> -0.020108915 | F4: =('Extracted Data'!F7-'Extracted Data'!F5)/'Extracted Data'!F5 -> -0.74255376 | G4: =AVERAGE('Extracted Data'!J6:J7) -> -0.009915604 | H4: =AVERAGE('Extracted Data'!K6:K7) -> -0.49168531 | I4: ='Extracted Data'!M7 -> 0.040652979 | J4: Revenue was relatively flat to down, while net income declined sharply; operating cash flow stayed positive.
A5: Apple | B5: AAPL | C5: 416161 | D5: 112010 | E5: =('Extracted Data'!E10-'Extracted Data'!E8)/'Extracted Data'!E8 -> 0.085774293 | F5: =('Extracted Data'!F10-'Extracted Data'!F8)/'Extracted Data'!F8 -> 0.15480179 | G5: =AVERAGE('Extracted Data'!J9:J10) -> 0.042237529 | H5: =AVERAGE('Extracted Data'!K9:K10) -> 0.080676055 | I5: ='Extracted Data'!M10 -> 0.26915064 | J5: Revenue and net income improved in 2025, but operating cash flow dipped from 2024 while remaining very strong.

Sheet Sources
A1: Company | B1: Fiscal Years Used | C1: Primary Source URL | D1: Notes
A2: Microsoft | B2: FY2023-FY2025 | C2: https://www.microsoft.com/investor/reports/ar25/index.html | D2: 2025 annual report gives income statement and cash flow for FY2023-FY2025; FY2023 balance sheet from FY2024 report.
A3: Microsoft supplemental | B3: FY2023 balance sheet | C3: https://www.microsoft.com/en-us/Investor/earnings/FY-2024-Q4/balance-sheets | D3: Used for 2023 total assets and liabilities.
A4: Tesla | B4: FY2023-FY2025 | C4: https://stocklight.com/stocks/us/nasdaq-tsla/tesla/annual-reports/nasdaq-tsla-2026-10K-26574326.pdf | D4: 2025 10-K shows all three years; FY2023 balance sheet corroborated from 2024 10-K.
A5: Tesla supplemental | B5: FY2023 balance sheet | C5: https://stocklight.com/stocks/us/nasdaq-tsla/tesla/annual-reports/nasdaq-tsla-2025-10K-25570807.pdf | D5: Used for 2023 total assets and liabilities.
A6: Apple | B6: FY2023-FY2025 | C6: https://www.sec.gov/Archives/edgar/data/320193/000032019325000079/aapl-20250927.htm | D6: 2025 10-K; FY2023 balance sheet from 2024 10-K.
A7: Apple supplemental | B7: FY2023 balance sheet | C7: https://www.sec.gov/Archives/edgar/data/320193/000032019324000123/aapl-20240928.htm | D7: Used for 2023 total assets and liabilities.
